cabrnet/__init__.py
cabrnet/main.py
cabrnet/main_gui.py
cabrnet/apps/bayesian_optimizer.py
cabrnet/apps/benchmark.py
cabrnet/apps/evaluate.py
cabrnet/apps/explain_global.py
cabrnet/apps/explain_local.py
cabrnet/apps/get_graph.py
cabrnet/apps/import.py
cabrnet/apps/show_latent_space.py
cabrnet/apps/train.py
cabrnet/archs/convnet/decision.py
cabrnet/archs/convnet/model.py
cabrnet/archs/custom_extractors/__init__.py
cabrnet/archs/custom_extractors/onnx_backbone.py
cabrnet/archs/generic/conv_extractor.py
cabrnet/archs/generic/decision.py
cabrnet/archs/generic/model.py
cabrnet/archs/pipnet/decision.py
cabrnet/archs/pipnet/model.py
cabrnet/archs/protopnet/decision.py
cabrnet/archs/protopnet/model.py
cabrnet/archs/protopool/decision.py
cabrnet/archs/protopool/model.py
cabrnet/archs/prototree/decision.py
cabrnet/archs/prototree/model.py
cabrnet/core/evaluation/local_perturbation_analysis.py
cabrnet/core/evaluation/relevance_analysis.py
cabrnet/core/interface/analysis_gui.py
cabrnet/core/interface/benchmark.py
cabrnet/core/interface/design_gui.py
cabrnet/core/interface/utils.py
cabrnet/core/interface/visualization.py
cabrnet/core/utils/custom_preprocess.py
cabrnet/core/utils/data.py
cabrnet/core/utils/exceptions.py
cabrnet/core/utils/image.py
cabrnet/core/utils/init.py
cabrnet/core/utils/monitoring.py
cabrnet/core/utils/optimizers.py
cabrnet/core/utils/parser.py
cabrnet/core/utils/prototypes.py
cabrnet/core/utils/save.py
cabrnet/core/utils/similarities.py
cabrnet/core/utils/system_info.py
cabrnet/core/utils/train.py
cabrnet/core/utils/transform.py
cabrnet/core/utils/tree.py
cabrnet/core/visualization/explainer.py
cabrnet/core/visualization/gradients.py
cabrnet/core/visualization/postprocess.py
cabrnet/core/visualization/prp_utils.py
cabrnet/core/visualization/upsampling.py
cabrnet/core/visualization/view.py
cabrnet/core/visualization/visualizer.py
cabrnet-1.2.dist-info/licenses/COPYING
cabrnet-1.2.dist-info/licenses/COPYING.LESSER
cabrnet-1.2.dist-info/METADATA
cabrnet-1.2.dist-info/WHEEL
cabrnet-1.2.dist-info/entry_points.txt
cabrnet-1.2.dist-info/top_level.txt
cabrnet-1.2.dist-info/RECORD
