Metadata-Version: 2.4
Name: cabrnet
Version: 1.2
Summary: Generic library for prototype-based classifiers
Author-email: Romain Xu-Darme <romain.xu-darme@cea.fr>, Aymeric Varasse <aymeric.varasse@cea.fr>
Maintainer-email: Romain Xu-Darme <romain.xu-darme@cea.fr>, Aymeric Varasse <aymeric.varasse@cea.fr>, Julien Girard-Satabin <julien.girard2@cea.fr>, Alban Grastien <alban.grastien@cea.fr>
Project-URL: Homepage, https://github.com/aiser-team/cabrnet
Project-URL: Issues, https://github.com/aiser-team/cabrnet/issues
Classifier: Programming Language :: Python :: 3
Classifier: License :: OSI Approved :: GNU Lesser General Public License v2 (LGPLv2)
Classifier: Operating System :: OS Independent
Requires-Python: <3.13,>=3.10
License-File: COPYING
License-File: COPYING.LESSER
Requires-Dist: torch>=2.0.0
Requires-Dist: torchvision>=0.13.0
Requires-Dist: numpy>=1.19.5
Requires-Dist: setuptools>=70.0.0
Requires-Dist: tqdm>=4.66.3
Requires-Dist: scipy>=1.11.3
Requires-Dist: loguru>=0.7.2
Requires-Dist: zenodo-get>=1.5.1
Requires-Dist: graphviz>=0.20.1
Requires-Dist: opencv-python-headless
Requires-Dist: captum>=0.7.0
Requires-Dist: py-cpuinfo~=9.0.0
Requires-Dist: gradio~=4.43.0
Requires-Dist: tensorboard>=2.17.0
Requires-Dist: ray[tune]~=2.34.0
Requires-Dist: optuna~=3.6.1
Requires-Dist: onnxruntime~=1.19.0
Requires-Dist: onnx~=1.19.1
Requires-Dist: onnx_graphsurgeon~=0.5.2
Requires-Dist: pacmap~=0.7.3
Requires-Dist: scikit-learn~=1.5.1
Requires-Dist: thop~=0.1.1
Provides-Extra: dev
Requires-Dist: black==24.10.0; extra == "dev"
Requires-Dist: build; extra == "dev"
Requires-Dist: pyright; extra == "dev"
Requires-Dist: twine; extra == "dev"
Provides-Extra: doc
Requires-Dist: mkdocs; extra == "doc"
Requires-Dist: pydoc-markdown; extra == "doc"
Requires-Dist: pymdown-extensions; extra == "doc"
Requires-Dist: python-markdown-math; extra == "doc"
Provides-Extra: legacy
Requires-Dist: gdown~=4.7.1; extra == "legacy"
Requires-Dist: requests~=2.32.0; extra == "legacy"
Requires-Dist: Augmentor~=0.2.12; extra == "legacy"
Dynamic: license-file
